pymscada_pycomm3-0.0.4.dist-info/METADATA
pymscada_pycomm3-0.0.4.dist-info/WHEEL
pymscada_pycomm3-0.0.4.dist-info/licenses/LICENSE
pymscada_pycomm3/__init__.py
pymscada_pycomm3/__main__.py
pymscada_pycomm3/demo/pycomm3.yaml
pymscada_pycomm3/demo/pymscada-pycomm3.service
pymscada_pycomm3/logix_client.py
pymscada_pycomm3/logix_map.py
pymscada_pycomm3-0.0.4.dist-info/RECORD
