Metadata-Version: 2.1
Name: pymscada-pycomm3
Version: 0.0.4
Summary: pycomm3 connector for pymscada
Author-Email: Jamie Walton <jamie@walton.net.nz>
License: GPL-3.0-or-later
Requires-Python: >=3.9
Requires-Dist: pymscada>=0.0.11
Requires-Dist: pycomm3>=1.2.14
